hunter/__init__.py
hunter/__main__.py
hunter/constants.py
hunter/formatters.py
hunter/main.py
hunter/parsers.py
hunter/utils/__init__.py
hunter/utils/ai.py
hunter/utils/errors.py
hunter/utils/fetcher.py
hunter/utils/progress.py
codename_hunter-0.1.3.dist-info/LICENSE
codename_hunter-0.1.3.dist-info/METADATA
codename_hunter-0.1.3.dist-info/WHEEL
codename_hunter-0.1.3.dist-info/entry_points.txt
codename_hunter-0.1.3.dist-info/top_level.txt
codename_hunter-0.1.3.dist-info/RECORD
