Metadata-Version: 2.1
Name: codename_hunter
Version: 0.1.3
Summary: A powerful tool for extracting and enhancing markdown content from web pages
Author-email: Joe <joevfernandez@gmail.com>
License: MIT
Project-URL: Homepage, https://github.com/joenandez/codename_hunter
Project-URL: Bug Tracker, https://github.com/joenandez/codename_hunter/issues
Project-URL: Documentation, https://github.com/joenandez/codename_hunter#readme
Keywords: markdown,web-scraping,content-extraction,ai-enhancement
Classifier: Development Status :: 4 - Beta
Classifier: Environment :: Console
Classifier: Intended Audience :: Developers
Classifier: Intended Audience :: End Users/Desktop
Classifier: License :: OSI Approved :: MIT License
Classifier: Operating System :: OS Independent
Classifier: Programming Language :: Python :: 3
Classifier: Programming Language :: Python :: 3.8
Classifier: Programming Language :: Python :: 3.9
Classifier: Programming Language :: Python :: 3.10
Classifier: Programming Language :: Python :: 3.11
Classifier: Topic :: Internet :: WWW/HTTP :: Dynamic Content
Classifier: Topic :: Text Processing :: Markup :: Markdown
Classifier: Topic :: Software Development :: Libraries :: Python Modules
Requires-Python: >=3.8
License-File: LICENSE
Requires-Dist: beautifulsoup4>=4.12.0
Requires-Dist: rich>=13.7.0
Requires-Dist: requests>=2.31.0
Requires-Dist: pyperclip>=1.8.2
Requires-Dist: aiohttp>=3.8.0
Requires-Dist: python-dotenv>=0.21.0
Requires-Dist: pydantic>=1.10.0
Provides-Extra: dev
Requires-Dist: pytest>=7.4.0; extra == "dev"
Requires-Dist: pytest-asyncio>=0.23.0; extra == "dev"
Requires-Dist: flake8>=6.1.0; extra == "dev"
